pytest_grader/__init__.py
pytest_grader/cli.py
pytest_grader/decorators.py
pytest_grader/lock_tests.py
pytest_grader/logger.py
pytest_grader/plugins.py
pytest_grader/unlock_tests.py
pytest_grader-0.1.2.dist-info/METADATA
pytest_grader-0.1.2.dist-info/WHEEL
pytest_grader-0.1.2.dist-info/entry_points.txt
pytest_grader-0.1.2.dist-info/top_level.txt
pytest_grader-0.1.2.dist-info/RECORD
