Metadata-Version: 2.4
Name: pytest-grader
Version: 0.1.2
Summary: Pytest extension for scoring programming assignments.
Classifier: Framework :: Pytest
Requires-Python: >=3.10
Requires-Dist: build>=1.3.0
Requires-Dist: pytest>=8
Requires-Dist: pyyaml>=6.0.2
Requires-Dist: sqlitedict>=2.1.0
Requires-Dist: twine>=6.1.0
